http_resource/__init__.py
http_resource/compat.py
http_resource/error.py
http_resource/resource.py
http_resource/transports.py
http_resource/utils.py
http_resource-0.1.2.dist-info/DESCRIPTION.rst
http_resource-0.1.2.dist-info/METADATA
http_resource-0.1.2.dist-info/RECORD
http_resource-0.1.2.dist-info/WHEEL
http_resource-0.1.2.dist-info/metadata.json
http_resource-0.1.2.dist-info/top_level.txt
